[{
    "title": "Lud-en-brume",
    "author": "Hope Mirrlees",
    "publisher": "Le livre de poche",
    "description": "Aux frontières de la Faërie, Lud-en-Brume est une cité prospère et paisible du pays de Dorimare. Mais les secrets hérités du royaume voisin ne sauraient rester indéfiniment dans l'ombre. Les fruits féeriques, drogue nocive et bannie de la société luddite, circulent dans la région. Ranulph semble en être victime, et son père, le Maire Nathaniel Chantecler, qui faisait jusqu'à maintenant régner la Loi d'une poigne molle et tranquille, se doit bientôt de faire l'impensable pour sauver son fils et sa cité. Mais heureusement pour Lud-en-Brume, Nathaniel est doté d'un esprit des plus pragmatiques... et d'une tête dans la lune !Écrit d'une plume ironique, dans un style riche et coloré, Lud-en-Brume est un chef-d'oeuvre inclassable de l'imaginaire.Préface de Neil Gaiman.Introduction de Douglas A. Anderson.Prix Elbakin.net 2016 du meilleur roman fantasy traduitTraduit de l'anglais par Julie Petonnet-Vincent.",
    "miniature_link": "https://images.epagine.fr/719/9782253083719_1_m.jpg",
    "isbn": "9782253083719",
    "rate": 0,
    "comment": null,
    "format": null,
    "google_id": "9782253083719",
    "series": null,
    "series_number": null,
    "language": "fr",
    "added_date": 1668116636955,
    "status": "to-read",
    "started_date": null,
    "finished_date": null, 
    "owned": false
}]


